Metadata-Version: 2.1
Name: gpaw
Version: 25.1.0
Summary: GPAW: DFT and beyond within the projector-augmented wave method
Home-page: https://gpaw.readthedocs.io/
Maintainer: GPAW-community
Maintainer-email: gpaw-users@listserv.fysik.dtu.dk
License: GPLv3+
Platform: unix
Classifier: Development Status :: 6 - Mature
Classifier: License :: OSI Approved :: GNU General Public License v3 or later (GPLv3+)
Classifier: Operating System :: OS Independent
Classifier: Programming Language :: Python :: 3
Classifier: Topic :: Scientific/Engineering :: Physics
Requires-Python: >=3.9
License-File: LICENSE
License-File: COPYING
Requires-Dist: ase>=3.23.0
Requires-Dist: numpy
Requires-Dist: scipy>=1.6.0
Provides-Extra: docs
Requires-Dist: sphinx-rtd-theme; extra == "docs"
Requires-Dist: sphinxcontrib-jquery; extra == "docs"
Requires-Dist: plotly; extra == "docs"
Requires-Dist: kaleido; extra == "docs"
Requires-Dist: graphviz; extra == "docs"
Requires-Dist: scikit-image; extra == "docs"
Provides-Extra: devel
Requires-Dist: flake8; extra == "devel"
Requires-Dist: mypy; extra == "devel"
Requires-Dist: pytest>=7.0.0; extra == "devel"
Requires-Dist: pytest-xdist; extra == "devel"
Requires-Dist: interrogate; extra == "devel"
